Winfo/__init__.py
Winfo/audio.py
Winfo/cpu.py
Winfo/disk.py
Winfo/ethernet.py
Winfo/gpu.py
Winfo/internet.py
Winfo/memory.py
Winfo/motherboard.py
Winfo/software.py
Winfo-0.0.4.dist-info/LICENSE
Winfo-0.0.4.dist-info/METADATA
Winfo-0.0.4.dist-info/WHEEL
Winfo-0.0.4.dist-info/top_level.txt
Winfo-0.0.4.dist-info/RECORD
