Metadata-Version: 2.1
Name: Winfo
Version: 0.0.4
Summary: Get information about your windows system
Author: BLUEAMETHYST Studios
Keywords: python,windows,util,information,system
Classifier: Intended Audience :: Developers
Classifier: Programming Language :: Python :: 3
Classifier: Operating System :: Microsoft :: Windows
License-File: LICENSE
